galileosky/__init__.py
galileosky/tags.py
galileosky-0.3.0.dist-info/LICENSE
galileosky-0.3.0.dist-info/METADATA
galileosky-0.3.0.dist-info/WHEEL
galileosky-0.3.0.dist-info/top_level.txt
galileosky-0.3.0.dist-info/RECORD
