Metadata-Version: 2.1
Name: galileosky
Version: 0.3.0
Summary: galileosky protocol implementation
Home-page: https://github.com/pikhovkin/galileosky
Author: Sergei Pikhovkin
Author-email: s@pikhovkin.ru
License: MIT
Platform: UNKNOWN
Classifier: Development Status :: 4 - Beta
Classifier: License :: OSI Approved :: MIT License
Classifier: Programming Language :: Python
Classifier: Programming Language :: Python :: 3
Classifier: Programming Language :: Python :: 3.6
Classifier: Programming Language :: Python :: 3.7
Classifier: Programming Language :: Python :: 3.8
Classifier: Programming Language :: Python :: 3.9
Classifier: Topic :: System :: Monitoring
Classifier: Topic :: Utilities
Requires-Python: >=3.6
Requires-Dist: libscrc (==1.3)
